__init__.py
example.py
piepal.py
piepal-0.1.0.dist-info/licenses/LICENSE
piepal-0.1.0.dist-info/METADATA
piepal-0.1.0.dist-info/WHEEL
piepal-0.1.0.dist-info/entry_points.txt
piepal-0.1.0.dist-info/top_level.txt
piepal-0.1.0.dist-info/RECORD
