Metadata-Version: 2.4
Name: piepal
Version: 0.1.0
Summary: PiePAL - PayPal observability tool
Author-email: Dmitry Ro <dmitry@falsetrue.io>
License: MIT
Requires-Python: >=3.7
License-File: LICENSE
Requires-Dist: python-dotenv==1.1.0
Requires-Dist: Requests==2.32.3
Requires-Dist: rich==14.0.0
Dynamic: license-file
